odoo/addons/tms_purchase/README.rst
odoo/addons/tms_purchase/__init__.py
odoo/addons/tms_purchase/__manifest__.py
odoo/addons/tms_purchase/i18n/tms_purchase.pot
odoo/addons/tms_purchase/models/__init__.py
odoo/addons/tms_purchase/models/fleet_vehicle.py
odoo/addons/tms_purchase/models/purchase_order.py
odoo/addons/tms_purchase/models/stock_move.py
odoo/addons/tms_purchase/models/tms_order.py
odoo/addons/tms_purchase/readme/CONTRIBUTORS.md
odoo/addons/tms_purchase/readme/CREDITS.md
odoo/addons/tms_purchase/readme/DESCRIPTION.md
odoo/addons/tms_purchase/readme/INSTALL.md
odoo/addons/tms_purchase/readme/MAINTAINERS.md
odoo/addons/tms_purchase/readme/USAGE.md
odoo/addons/tms_purchase/static/description/icon.png
odoo/addons/tms_purchase/static/description/icon.svg
odoo/addons/tms_purchase/static/description/index.html
odoo/addons/tms_purchase/views/fleet_vehicle_views.xml
odoo/addons/tms_purchase/views/purchase_order_views.xml
odoo/addons/tms_purchase/views/tms_order.xml
odoo_addon_tms_purchase-17.0.1.0.0.1.dist-info/METADATA
odoo_addon_tms_purchase-17.0.1.0.0.1.dist-info/WHEEL
odoo_addon_tms_purchase-17.0.1.0.0.1.dist-info/top_level.txt
odoo_addon_tms_purchase-17.0.1.0.0.1.dist-info/RECORD
